{
  "streams": [
    {
      "title": "A Tu z innego konta",
      "description": "Walka z Wiatrakami to jest",
      "userId": "109469224685681579048",
      "id": 2
    },
    {
      "title": "qqqwweee",
      "description": "qweqweqwe",
      "userId": "103372450038356295670",
      "id": 5
    },
    {
      "title": "qweqwewqe",
      "description": "s",
      "userId": "103372450038356295670",
      "id": 7
    },
    {
      "title": "sadad",
      "description": "saddasa",
      "userId": "103372450038356295670",
      "id": 8
    },
    {
      "title": "xxxxxxxxxxxxxxxxxx",
      "description": "xxxxxxxxxxxxxxxxxxxxx",
      "userId": "103372450038356295670",
      "id": 9
    },
    {
      "title": "xxxxxxxxxxx",
      "description": "xxxxxxxxxxxxxxxx",
      "userId": "103372450038356295670",
      "id": 10
    },
    {
      "title": "zxcxzcsd",
      "description": "fzfzc",
      "userId": "103372450038356295670",
      "id": 11
    },
    {
      "title": "a",
      "description": "a",
      "userId": "103372450038356295670",
      "id": 12
    },
    {
      "title": "a",
      "description": "a",
      "userId": "103372450038356295670",
      "id": 13
    },
    {
      "title": "asdgf",
      "description": "gdsgdsgdsgds",
      "userId": "103372450038356295670",
      "id": 14
    }
  ]
}